datch/__init__.py
datch/datch.py
datch/errors.py
datch/version.py
datch-0.1.4.dist-info/LICENSE
datch-0.1.4.dist-info/METADATA
datch-0.1.4.dist-info/WHEEL
datch-0.1.4.dist-info/top_level.txt
datch-0.1.4.dist-info/RECORD
