Metadata-Version: 2.1
Name: datch
Version: 0.1.4
Summary: DatCh checks data for inconsistancies.
Home-page: http://www.maanrijp.nl
Author: Arvid Hahné
Author-email: arvid@maanrijp.nl
License: GNU GPLv3
Platform: UNKNOWN
Classifier: Development Status :: 5 - Production/Stable
Classifier: Intended Audience :: Science/Research
Classifier: Programming Language :: Python :: 3.7
